{
  "programs": [
    {
      "id": "hew-massage-therapy",
      "slug": "massage-therapy",
      "name": "Massage Therapy Training",
      "audience": "student",
      "quickFacts": [
        "Certificate Included",
        "Expert Instructor",
        "Hands-On"
      ],
      "highlights": [
        {
          "icon": "hammer",
          "label": "Hands-On Learning",
          "description": "Practice techniques on real clients from day one in a professional spa environment."
        },
        {
          "icon": "users",
          "label": "Small Class Sizes",
          "description": "Personal attention and individualized instruction in an intimate learning setting."
        },
        {
          "icon": "badge-check",
          "label": "Certificate Included",
          "description": "Receive a professional certificate upon successful completion of the program."
        },
        {
          "icon": "graduation-cap",
          "label": "Exam/Career Ready",
          "description": "Graduate with the skills needed to work in spas, wellness centres, or start your own practice or take the exam to become a registered massage therapist."
        }
      ],
      "tagline": "Master the art of therapeutic massage",
      "outcome": "Become a certified massage therapist ready for professional practice",
      "description": "This 7-week Massage Therapy Program trains students to provide Swedish, Deep Tissue, Aromatherapy, and Hot Stone massage while mastering professional workplace skills such as client consultation, workspace sanitization, session preparation, customer service, and retail practices.",
      "capabilities": [
        {
          "outcome": "Operate **professionally** in a real Massage Therapy environment",
          "competencies": [
            {
              "statement": "Meet and greet clients professionally"
            },
            {
              "statement": "Receive and direct clients appropriately"
            },
            {
              "statement": "Conduct client consultation and preparation for therapy"
            },
            {
              "statement": "Maintain workspace sanitization, safety, and hygiene"
            },
            {
              "statement": "Plan and organize massage therapy work"
            },
            {
              "statement": "Deliver quality service and maintain customer relations"
            },
            {
              "statement": "Perform interactive workplace communication"
            }
          ]
        },
        {
          "outcome": "Apply **Anatomy and Physiology** knowledge to massage therapy",
          "competencies": [
            {
              "statement": "Understand the muscular and skeletal system"
            },
            {
              "statement": "Apply anatomy and physiology knowledge to massage therapy"
            },
            {
              "statement": "Identify muscles used in Swedish, Deep Tissue, and Hot Stone massage"
            }
          ]
        },
        {
          "outcome": "Perform full-body **Swedish Massage** safely and effectively",
          "competencies": [
            {
              "statement": "Perform effleurage, petrissage, friction, tapotement, and vibration"
            },
            {
              "statement": "Deliver a full-body Swedish massage session"
            },
            {
              "statement": "Perform Swedish massage using aromatic oils"
            },
            {
              "statement": "Maintain client comfort and safe technique during massage"
            }
          ]
        },
        {
          "outcome": "Deliver **Deep Tissue Massage** with appropriate pressure and control",
          "competencies": [
            {
              "statement": "Understand principles and benefits of deep tissue massage"
            },
            {
              "statement": "Apply deep tissue techniques to major muscle groups"
            },
            {
              "statement": "Manage client pressure and comfort during deep tissue massage"
            }
          ]
        },
        {
          "outcome": "Perform **Aromatherapy Massage** using essential oils safely",
          "competencies": [
            {
              "statement": "Understand the fundamentals of aromatherapy"
            },
            {
              "statement": "Identify essential oils, their properties, and safety considerations"
            },
            {
              "statement": "Blend oils and perform aromatherapy massage safely"
            }
          ]
        },
        {
          "outcome": "Perform full-body **Hot Stone Massage** treatments",
          "competencies": [
            {
              "statement": "Use heated stones safely during massage"
            },
            {
              "statement": "Apply proper placement and technique with hot stones"
            },
            {
              "statement": "Integrate hot stones with other massage techniques"
            },
            {
              "statement": "Deliver a full-body hot stone massage session"
            }
          ]
        },
        {
          "outcome": "Close sessions professionally and support **Post-Treatment Care**",
          "competencies": [
            {
              "statement": "Close massage sessions professionally"
            },
            {
              "statement": "Provide appropriate product recommendations"
            },
            {
              "statement": "Provide post-treatment client care guidance"
            },
            {
              "statement": "Perform retail and client follow-up procedures"
            }
          ]
        }
      ],
      "groupId": "massage-therapy",
      "cycleIds": [
        "hew-massage-20260107",
        "hew-massage-20260225",
        "hew-massage-20260415",
        "hew-massage-20260603"
      ],
      "media": {
        "galleryIds": [
          "hew-massage-model",
          "hew-reception-area"
        ]
      },
      "testimonials": [
        {
          "author": "Angella ShandDyer",
          "content": "I happen to have had first hand experience with this lady as my trainer when i was doing the makeup artistry course. She is very patient and technically sound. Her training techniques definitely moved my skill level up several notches. Thank you Alicia for all the encouragement you gave…you made me beleive I could do it ..and I did.",
          "date": "2025-12-15",
          "rating": 4,
          "relation": "Student",
          "link": "https://maps.app.goo.gl/LDy4TzBmTT811w4N9",
          "source": "google"
        },
        {
          "author": "Rickae Crossman",
          "content": "Dear Miss Davis, I wanted to take a moment to express my gratitude for all the support and guidance you've provided throughout this course. Your passion for teaching and dedication to helping us learn has truly made a difference in my experience. Thank you for being patient, approachable, and always willing to help. I've learned so much from you, and I appreciate the effort you put into making our classes engaging and meaningful. Thank you once again for everything! Rickae",
          "date": "2025-12-15",
          "rating": 5,
          "relation": "Student",
          "source": "other"
        }
      ]
    },
    {
      "id": "hew-advanced-massage-therapy",
      "slug": "advanced-massage-therapy",
      "name": "Advanced Massage Therapy Program",
      "audience": "student",
      "quickFacts": [
        "Advanced Techniques",
        "Expert Instructor",
        "Certificate Included",
        "Specialized Modalities"
      ],
      "highlights": [
        {
          "icon": "hammer",
          "label": "Advanced Techniques",
          "description": "Master specialized massage modalities including sports massage, trigger point therapy, and myofascial release."
        },
        {
          "icon": "users",
          "label": "Small Class Sizes",
          "description": "Intensive, personalized instruction in advanced therapeutic techniques."
        },
        {
          "icon": "badge-check",
          "label": "Advanced Certificate",
          "description": "Receive an advanced certificate upon successful completion, demonstrating mastery of advanced techniques."
        },
        {
          "icon": "graduation-cap",
          "label": "Professional Advancement",
          "description": "Elevate your practice with advanced skills for specialized client needs and career growth."
        }
      ],
      "tagline": "Elevate your massage therapy practice with advanced techniques",
      "outcome": "Become an advanced massage therapist with specialized skills for complex client needs",
      "description": "Our Advanced Massage Therapy program builds upon fundamental massage skills to teach specialized techniques for addressing complex client needs. Students will learn advanced modalities including sports massage, trigger point therapy, myofascial release, and injury rehabilitation techniques. This program is designed for practicing massage therapists seeking to expand their skill set and advance their careers.",
      "whatYouWillLearn": [
        {
          "heading": "Advanced Assessment",
          "items": [
            {
              "id": "advanced-anatomy",
              "title": "Advanced Anatomy & Pathology",
              "blurb": "Deep dive into musculoskeletal anatomy, common pathologies, and their implications for massage therapy.",
              "tag": "Foundations"
            },
            {
              "id": "assessment-techniques",
              "title": "Advanced Assessment Techniques",
              "blurb": "Learn comprehensive client assessment methods including postural analysis and range of motion testing."
            }
          ]
        },
        {
          "heading": "Specialized Techniques",
          "items": [
            {
              "id": "sports-massage",
              "title": "Sports Massage",
              "blurb": "Master pre-event, post-event, and maintenance sports massage techniques for athletes.",
              "tag": "Core Skill"
            },
            {
              "id": "trigger-point-therapy",
              "title": "Trigger Point Therapy",
              "blurb": "Advanced techniques for identifying and releasing trigger points to alleviate chronic pain."
            },
            {
              "id": "myofascial-release",
              "title": "Myofascial Release",
              "blurb": "Learn specialized techniques for releasing fascial restrictions and improving mobility."
            },
            {
              "id": "injury-rehab",
              "title": "Injury Rehabilitation",
              "blurb": "Develop skills for working with clients recovering from injuries and surgeries."
            }
          ]
        },
        {
          "heading": "Professional Excellence",
          "items": [
            {
              "id": "treatment-planning",
              "title": "Advanced Treatment Planning",
              "blurb": "Create comprehensive, multi-session treatment plans for complex client conditions.",
              "tag": "Hands-on"
            },
            {
              "id": "client-communication",
              "title": "Advanced Client Communication",
              "blurb": "Master communication techniques for explaining complex treatments and managing client expectations."
            },
            {
              "id": "practice-development",
              "title": "Advanced Practice Development",
              "blurb": "Build skills for developing specialized services and growing your advanced practice.",
              "tag": "Career Ready"
            }
          ]
        }
      ],
      "groupId": "massage-therapy",
      "cycleIds": [
        "hew-advanced-massage-20260107",
        "hew-advanced-massage-20260225",
        "hew-advanced-massage-20260415",
        "hew-advanced-massage-20260603"
      ],
      "media": {
        "galleryIds": [
          "hew-massage-model",
          "hew-reception-area"
        ]
      }
    }
  ]
}